reflex_myui/__init__.py
reflex_myui/calculator.py
reflex_myui/footer.py
reflex_myui/header.py
reflex_myui/myui.py
reflex_myui/side_menu.py
reflex_myui/state.py
reflex_myui/templates.py
reflex_myui-0.0.3.dist-info/METADATA
reflex_myui-0.0.3.dist-info/WHEEL
reflex_myui-0.0.3.dist-info/RECORD
