Metadata-Version: 2.3
Name: reflex_myui
Version: 0.0.3
Summary: A custom UI library for my Reflex apps.
Author: Tyler
Requires-Python: >=3.11,<4.0
Classifier: Programming Language :: Python :: 3
Classifier: Programming Language :: Python :: 3.11
Classifier: Programming Language :: Python :: 3.12
Classifier: Programming Language :: Python :: 3.13
Requires-Dist: reflex (>=0.7.5)
Requires-Dist: reflex-simpleicons (>=0.0.6)
